AnalysisCommits/__init__.py
AnalysisCommits/control_commit.py
AnalysisCommits/date_tick_label.py
AnalysisCommits/grouped_bar_chart.py
AnalysisCommits/grouped_bar_chart_formA.py
AnalysisCommits/grouped_bar_chart_formB.py
AnalysisCommits/gui_commit.py
AnalysisCommits/horizontal_bar_chart.py
AnalysisCommits/labeling_pie_and_a_donut.py
AnalysisCommits/load_commit_info.py
AnalysisCommits/reference_to_thread.py
AnalysisCommits/search_commit_info.py
AnalysisCommits/ssh_control.py
AnalysisCommits-0.9.1.dist-info/METADATA
AnalysisCommits-0.9.1.dist-info/WHEEL
AnalysisCommits-0.9.1.dist-info/top_level.txt
AnalysisCommits-0.9.1.dist-info/RECORD
