Metadata-Version: 2.1
Name: AnalysisCommits
Version: 0.9.1
Summary: Info.
Home-page: UNKNOWN
Author: jongduk.kim
Author-email: jongduk.kim@klge.com
License: UNKNOWN
Platform: UNKNOWN
Requires-Python: >=3
Requires-Dist: pandas
Requires-Dist: matplotlib
Requires-Dist: numpy
Requires-Dist: paramiko
